wataproclient/__init__.py
wataproclient/client.py
wataproclient/exceptions.py
wataproclient/http.py
wataproclient/logging_config.py
wataproclient/manager.py
wataproclient/modules/__init__.py
wataproclient/modules/base.py
wataproclient/modules/links.py
wataproclient/modules/transactions.py
wataproclient/modules/webhooks.py
wataproclient-1.3.2.dist-info/METADATA
wataproclient-1.3.2.dist-info/WHEEL
wataproclient-1.3.2.dist-info/top_level.txt
wataproclient-1.3.2.dist-info/RECORD
