Metadata-Version: 2.4
Name: wataproclient
Version: 1.3.2
Summary: Асинхронный клиент для платежного API WATA
Author-email: WATA API Client Developer <keemor821@gmail.com>
Classifier: Development Status :: 4 - Beta
Classifier: Intended Audience :: Developers
Classifier: Programming Language :: Python :: 3
Classifier: Programming Language :: Python :: 3.7
Classifier: Programming Language :: Python :: 3.8
Classifier: Programming Language :: Python :: 3.9
Classifier: Programming Language :: Python :: 3.10
Classifier: Programming Language :: Python :: 3.11
Requires-Python: >=3.7
Requires-Dist: aiohttp>=3.7.4
Requires-Dist: cryptography
